{
  "date": "2026-07-03",
  "lastUpdated": "2026-07-03T01:00:05.716Z",
  "source": "update-dashboard-script",
  "snapshotPath": "/Users/alfonsogarzabot/.openclaw/workspace/market-snapshot.json",
  "marketMode": "Risk-Off",
  "fearGreed": "21/100 — Extreme Fear",
  "btcDominance": "55.7%",
  "spyTrend": "$744.78 (-0.27% today)",
  "qqqTrend": "$712.60 (-3.23% today)",
  "treasury10y": "4.49% (+0.22% today)",
  "dxy": "100.96 (-0.42% today)",
  "btcStructure": "$61,237 (+2.54% 24h | +2.55% 7d)",
  "ethPrice": "$1,695 (+5.70% 24h | +8.30% 7d)",
  "solPrice": "$80.74 (+4.65% 24h | +19.39% 7d)",
  "totalCryptoMarketCap": "$2.21T",
  "topOpportunity": "Check Vega's 7am Telegram brief for trade ideas",
  "topRisk": "Fear & Greed at 21/100 — monitor for sentiment shifts"
}