{
  "date": "2026-07-22",
  "lastUpdated": "2026-07-22T13:00:05.328Z",
  "source": "update-dashboard-script",
  "snapshotPath": "/Users/alfonsogarzabot/.openclaw/workspace/market-snapshot.json",
  "marketMode": "Risk-Off",
  "fearGreed": "33/100 — Fear",
  "btcDominance": "56.7%",
  "spyTrend": "$748.28 (+0.67% today)",
  "qqqTrend": "$708.97 (+1.96% today)",
  "treasury10y": "4.63% (+0.13% today)",
  "dxy": "101.14 (-0.04% today)",
  "btcStructure": "$65,601 (-1.36% 24h | +1.54% 7d)",
  "ethPrice": "$1,916 (-1.31% 24h | +2.08% 7d)",
  "solPrice": "$77.17 (-1.61% 24h | -0.17% 7d)",
  "totalCryptoMarketCap": "$2.32T",
  "topOpportunity": "Check Vega's 7am Telegram brief for trade ideas",
  "topRisk": "Fear & Greed at 33/100 — monitor for sentiment shifts"
}