{
  "date": "2026-06-17",
  "lastUpdated": "2026-06-17T01:00:05.856Z",
  "source": "update-dashboard-script",
  "snapshotPath": "/Users/alfonsogarzabot/.openclaw/workspace/market-snapshot.json",
  "marketMode": "Risk-Off",
  "fearGreed": "22/100 — Extreme Fear",
  "btcDominance": "56.3%",
  "spyTrend": "$750.33 (+1.16% today)",
  "qqqTrend": "$729.86 (+1.18% today)",
  "treasury10y": "4.43% (-0.92% today)",
  "dxy": "99.52 (-0.11% today)",
  "btcStructure": "$65,696 (-0.88% 24h | +6.56% 7d)",
  "ethPrice": "$1,793 (+0.11% 24h | +9.41% 7d)",
  "solPrice": "$73.35 (-0.90% 24h | +12.96% 7d)",
  "totalCryptoMarketCap": "$2.34T",
  "topOpportunity": "Check Vega's 7am Telegram brief for trade ideas",
  "topRisk": "Fear & Greed at 22/100 — monitor for sentiment shifts"
}