{
  "date": "2026-06-13",
  "lastUpdated": "2026-06-13T15:00:06.080Z",
  "source": "update-dashboard-script",
  "snapshotPath": "/Users/alfonsogarzabot/.openclaw/workspace/market-snapshot.json",
  "marketMode": "Risk-Off",
  "fearGreed": "13/100 — Extreme Fear",
  "btcDominance": "56.5%",
  "spyTrend": "$741.75 (+2.25% today)",
  "qqqTrend": "$721.34 (+3.99% today)",
  "treasury10y": "4.49% (+0.54% today)",
  "dxy": "99.81 (-0.05% today)",
  "btcStructure": "$64,184 (+0.41% 24h | +5.59% 7d)",
  "ethPrice": "$1,679 (-0.17% 24h | +7.84% 7d)",
  "solPrice": "$68.18 (+0.34% 24h | +8.39% 7d)",
  "totalCryptoMarketCap": "$2.28T",
  "topOpportunity": "Check Vega's 7am Telegram brief for trade ideas",
  "topRisk": "Fear & Greed at 13/100 — monitor for sentiment shifts"
}