{
  "date": "2026-06-25",
  "lastUpdated": "2026-06-25T21:00:04.684Z",
  "source": "update-dashboard-script",
  "snapshotPath": "/Users/alfonsogarzabot/.openclaw/workspace/market-snapshot.json",
  "marketMode": "Risk-Off",
  "fearGreed": "12/100 — Extreme Fear",
  "btcDominance": "55.8%",
  "spyTrend": "$734.30 (+0.10% today)",
  "qqqTrend": "$716.38 (+0.38% today)",
  "treasury10y": "4.39% (-0.23% today)",
  "dxy": "101.44 (-0.17% today)",
  "btcStructure": "$59,313 (-2.31% 24h | -5.27% 7d)",
  "ethPrice": "$1,557 (-3.20% 24h | -7.48% 7d)",
  "solPrice": "$66.06 (-2.38% 24h | -3.73% 7d)",
  "totalCryptoMarketCap": "$2.13T",
  "topOpportunity": "Check Vega's 7am Telegram brief for trade ideas",
  "topRisk": "Fear & Greed at 12/100 — monitor for sentiment shifts"
}