{
  "date": "2026-04-16",
  "lastUpdated": "2026-04-16T17:00:05.985Z",
  "source": "update-dashboard-script",
  "snapshotPath": "/Users/alfonsogarzabot/.openclaw/workspace/market-snapshot.json",
  "marketMode": "Risk-Off",
  "fearGreed": "23/100 — Extreme Fear",
  "btcDominance": "57.0%",
  "spyTrend": "$700.83 (+0.92% today)",
  "qqqTrend": "$640.00 (+1.81% today)",
  "treasury10y": "4.30% (+0.49% today)",
  "dxy": "98.26 (+0.20% today)",
  "btcStructure": "$74,214 (+0.25% 24h | +4.34% 7d)",
  "ethPrice": "$2,317 (-1.14% 24h | +6.44% 7d)",
  "solPrice": "$85.97 (+1.63% 24h | +4.65% 7d)",
  "totalCryptoMarketCap": "$2.61T",
  "topOpportunity": "Check Vega's 7am Telegram brief for trade ideas",
  "topRisk": "Fear & Greed at 23/100 — monitor for sentiment shifts"
}