{
  "date": "2026-05-18",
  "lastUpdated": "2026-05-18T01:00:05.679Z",
  "source": "update-dashboard-script",
  "snapshotPath": "/Users/alfonsogarzabot/.openclaw/workspace/market-snapshot.json",
  "marketMode": "Risk-Off",
  "fearGreed": "28/100 — Fear",
  "btcDominance": "58.3%",
  "spyTrend": "$739.17 (-0.42% today)",
  "qqqTrend": "$708.93 (-0.81% today)",
  "treasury10y": "4.59% (+3.00% today)",
  "dxy": "99.38 (+0.11% today)",
  "btcStructure": "$77,114 (-0.96% 24h | -5.99% 7d)",
  "ethPrice": "$2,112 (-2.95% 24h | -11.03% 7d)",
  "solPrice": "$85.16 (-1.13% 24h | -11.50% 7d)",
  "totalCryptoMarketCap": "$2.65T",
  "topOpportunity": "Check Vega's 7am Telegram brief for trade ideas",
  "topRisk": "Fear & Greed at 28/100 — monitor for sentiment shifts"
}