{
  "lastUpdated": "2026-05-19T13:00:04.220Z",
  "source": "update-dashboard-script",
  "snapshotPath": "/Users/alfonsogarzabot/.openclaw/workspace/market-snapshot.json",
  "marketMode": "Risk-Off",
  "fearGreed": "25/100 — Extreme Fear",
  "btcDominance": "58.2%",
  "spyTrend": "$738.65 (-1.27% today)",
  "qqqTrend": "$705.88 (-1.93% today)",
  "treasury10y": "4.62% (-0.09% today)",
  "dxy": "99.24 (+0.27% today)",
  "btcStructure": "$76,897 (-0.73% 24h | -4.63% 7d)",
  "ethPrice": "$2,117 (-1.34% 24h | -7.36% 7d)",
  "solPrice": "$84.69 (-0.95% 24h | -10.81% 7d)",
  "totalCryptoMarketCap": "$2.64T",
  "topOpportunity": "Check Vega's 7am Telegram brief for trade ideas",
  "topRisk": "Fear & Greed at 25/100 — monitor for sentiment shifts"
}