{
  "lastUpdated": "2026-07-06T17:00:07.617Z",
  "source": "update-dashboard-script",
  "snapshotPath": "/Users/alfonsogarzabot/.openclaw/workspace/market-snapshot.json",
  "marketMode": "Risk-Off",
  "fearGreed": "24/100 — Extreme Fear",
  "btcDominance": "55.8%",
  "spyTrend": "$750.46 (+0.63% today)",
  "qqqTrend": "$723.43 (-0.24% today)",
  "treasury10y": "4.48% (-0.00% today)",
  "dxy": "100.98 (+0.12% today)",
  "btcStructure": "$63,668 (+1.72% 24h | +7.33% 7d)",
  "ethPrice": "$1,791 (+1.09% 24h | +13.49% 7d)",
  "solPrice": "$81.99 (+1.18% 24h | +12.10% 7d)",
  "totalCryptoMarketCap": "$2.29T",
  "topOpportunity": "Check Vega's 7am Telegram brief for trade ideas",
  "topRisk": "Fear & Greed at 24/100 — monitor for sentiment shifts"
}