{
  "lastUpdated": "2026-05-05T19:00:06.696Z",
  "source": "update-dashboard-script",
  "snapshotPath": "/Users/alfonsogarzabot/.openclaw/workspace/market-snapshot.json",
  "marketMode": "Neutral",
  "fearGreed": "50/100 — Neutral",
  "btcDominance": "58.9%",
  "spyTrend": "$724.33 (+0.51% today)",
  "qqqTrend": "$682.31 (+1.21% today)",
  "treasury10y": "4.42% (-0.63% today)",
  "dxy": "98.45 (-0.02% today)",
  "btcStructure": "$81,507 (+1.81% 24h | +7.09% 7d)",
  "ethPrice": "$2,372 (+0.51% 24h | +3.78% 7d)",
  "solPrice": "$85.84 (+1.35% 24h | +2.75% 7d)",
  "totalCryptoMarketCap": "$2.77T",
  "topOpportunity": "Check Vega's 7am Telegram brief for trade ideas",
  "topRisk": "Fear & Greed at 50/100 — monitor for sentiment shifts"
}