{
  "lastUpdated": "2026-05-21T13:00:02.328Z",
  "source": "update-dashboard-script",
  "snapshotPath": "/Users/alfonsogarzabot/.openclaw/workspace/market-snapshot.json",
  "marketMode": "Risk-Off",
  "fearGreed": "29/100 — Fear",
  "btcDominance": "58.2%",
  "spyTrend": "$741.25 (+0.35% today)",
  "qqqTrend": "$713.15 (+1.03% today)",
  "treasury10y": "4.61% (+0.77% today)",
  "dxy": "99.30 (+0.19% today)",
  "btcStructure": "$77,220 (-0.36% 24h | -2.58% 7d)",
  "ethPrice": "$2,116 (-0.80% 24h | -6.15% 7d)",
  "solPrice": "$85.68 (+0.75% 24h | -5.48% 7d)",
  "totalCryptoMarketCap": "$2.66T",
  "topOpportunity": "Check Vega's 7am Telegram brief for trade ideas",
  "topRisk": "Fear & Greed at 29/100 — monitor for sentiment shifts"
}